gkutils/__init__.py
gkutils/__version__.py
gkutils/commonutils/__init__.py
gkutils/commonutils/bruteForceConeSearchATLAS.py
gkutils/commonutils/coneSearchCassandra.py
gkutils/commonutils/far.py
gkutils/commonutils/generalutils.py
gkutils/commonutils/generalutils_backup.py
gkutils/commonutils/getCSVColumnSubset.py
gkutils/commonutils/getTestSherlockData.py
gkutils/commonutils/mputils.py
gkutils/commonutils/test.py
gkutils/commonutils/testReadGenericDataFile.py
gkutils/commonutils/testregex.py
gkutils-0.3.10.dist-info/LICENSE
gkutils-0.3.10.dist-info/METADATA
gkutils-0.3.10.dist-info/WHEEL
gkutils-0.3.10.dist-info/entry_points.txt
gkutils-0.3.10.dist-info/top_level.txt
gkutils-0.3.10.dist-info/RECORD
