Metadata-Version: 2.1
Name: gkutils
Version: 0.3.10
Summary: A collection useful utilities - mostly related to astronomy
Home-page: https://github.com/genghisken/gkutils
Author: genghisken
Author-email: ken.w.smith@gmail.com
License: MIT
Classifier: Development Status :: 4 - Beta
Classifier: License :: OSI Approved :: MIT License
Classifier: Programming Language :: Python :: 3.6
Classifier: Topic :: Utilities
Requires-Python: >=3.6
License-File: LICENSE
Requires-Dist: pyyaml
Requires-Dist: docopt
Requires-Dist: numpy
